nidatasets/__init__.py
nidatasets-0.1.0.dist-info/LICENSE
nidatasets-0.1.0.dist-info/METADATA
nidatasets-0.1.0.dist-info/WHEEL
nidatasets-0.1.0.dist-info/top_level.txt
nidatasets-0.1.0.dist-info/RECORD
