Metadata-Version: 2.1
Name: nidatasets
Version: 0.1.0
Summary: Convenient access to preprocessed brain imaging data.
Home-page: https://feilong.github.io/nidatasets/
Author: Ma Feilong
Author-email: mafeilong@gmail.com
Project-URL: Bug Tracker, https://github.com/feilong/nidatasets/issues
Project-URL: Source Code, https://github.com/feilong/nidatasets
Keywords: brain,fmri,cortex,neuroscience,neuroimaging,surface
Classifier: Programming Language :: Python :: 3 :: Only
Classifier: Programming Language :: Python :: 3.6
Classifier: Programming Language :: Python :: 3.7
Classifier: Programming Language :: Python :: 3.8
Classifier: Programming Language :: Python :: 3.9
Classifier: Programming Language :: Python :: 3.10
Requires-Python: >=3.6
License-File: LICENSE
Requires-Dist: numpy
Requires-Dist: scipy
Requires-Dist: datalad
Requires-Dist: surface-spaces
Provides-Extra: tests
Requires-Dist: pytest ; extra == 'tests'
